{
  "/dress-types": {
    "get": {
      "tags": ["Dresses - Types"],
      "summary": "Get all dress types",
      "description": "Retrieve all dress types that are not soft deleted. Results are ordered alphabetically by name.",
      "operationId": "getDressTypes",
      "security": [{ "bearerAuth": [] }],
      "responses": {
        "200": {
          "description": "✅ Successfully retrieved dress types",
          "content": {
            "application/json": {
              "schema": { "$ref": "#/components/schemas/GetDressTypesResponse" },
              "example": {
                "success": true,
                "data": [
                  {
                    "id": "5d91f8c3-4a17-4a3a-81f5-df345c65b912",
                    "name": "Robe de soirée",
                    "description": "Tenue de soirée élégante"
                  },
                  {
                    "id": "a8f61e24-69a8-423e-903f-9a93358e4e99",
                    "name": "Robe de mariée",
                    "description": "Robe blanche pour cérémonie"
                  }
                ]
              }
            }
          }
        },
        "500": {
          "description": "💥 Failed to fetch dress types",
          "content": {
            "application/json": {
              "schema": { "$ref": "#/components/schemas/ErrorResponse" },
              "example": { "success": false, "error": "Failed to fetch dress types" }
            }
          }
        }
      }
    }
  }
}